{"dependencies":[{"name":"/home/xpc/文档/个人代码/个人学习/mookvideo/package.json","includedInParent":true,"mtime":1526917896648},{"name":"./../../plugin/video","loc":{"line":1,"column":20}},{"name":"./../../plugin/videojs-contrib-hls","loc":{"line":2,"column":7}}],"generated":{"js":"'use strict';\n\nvar _video = require('./../../plugin/video');\n\nvar _video2 = _interopRequireDefault(_video);\n\nrequire('./../../plugin/videojs-contrib-hls');\n\nfunction _interopRequireDefault(obj) { return obj && obj.__esModule ? obj : { default: obj }; }\n\nvar myPlayer = (0, _video2.default)('my-player');\nmyPlayer.play();","map":{"mappings":[{"generated":{"line":3,"column":0},"source":"source/videojs/index.js","original":{"line":1,"column":0}},{"generated":{"line":7,"column":0},"source":"source/videojs/index.js","original":{"line":2,"column":0}},{"generated":{"line":11,"column":0},"source":"source/videojs/index.js","original":{"line":3,"column":0}},{"name":"myPlayer","generated":{"line":11,"column":4},"source":"source/videojs/index.js","original":{"line":3,"column":4}},{"generated":{"line":11,"column":15},"source":"source/videojs/index.js","original":{"line":3,"column":15}},{"generated":{"line":11,"column":36},"source":"source/videojs/index.js","original":{"line":3,"column":23}},{"generated":{"line":11,"column":47},"source":"source/videojs/index.js","original":{"line":3,"column":15}},{"generated":{"line":11,"column":48},"source":"source/videojs/index.js","original":{"line":3,"column":0}},{"name":"myPlayer","generated":{"line":12,"column":0},"source":"source/videojs/index.js","original":{"line":4,"column":0}},{"name":"play","generated":{"line":12,"column":9},"source":"source/videojs/index.js","original":{"line":4,"column":9}},{"generated":{"line":12,"column":13},"source":"source/videojs/index.js","original":{"line":4,"column":0}}],"sources":{"source/videojs/index.js":"import videojs from './../../plugin/video'\nimport './../../plugin/videojs-contrib-hls'\nvar myPlayer = videojs('my-player');\nmyPlayer.play();"},"lineCount":null}},"hash":"eacb5da7b0e78e381c0bfbf9a3a51fd3","cacheData":{"env":{}}}